ai_cloudscraper-3.8.1.dist-info/licenses/LICENSE
cloudscraper/__init__.py
cloudscraper/adaptive_timing.py
cloudscraper/advanced_fingerprinting.py
cloudscraper/anti_detection.py
cloudscraper/async_cloudscraper.py
cloudscraper/behavioral_simulation.py
cloudscraper/browser_helper.py
cloudscraper/challenge_analyzer.py
cloudscraper/challenge_predictor.py
cloudscraper/challenge_response_system.py
cloudscraper/circuit_breaker.py
cloudscraper/cloudflare.py
cloudscraper/cloudflare_v2.py
cloudscraper/cloudflare_v3.py
cloudscraper/config.py
cloudscraper/cookie_manager.py
cloudscraper/enhanced_error_handling.py
cloudscraper/enhanced_spoofing.py
cloudscraper/exceptions.py
cloudscraper/help.py
cloudscraper/hybrid_engine.py
cloudscraper/hybrid_solver.py
cloudscraper/improved_bypass_demo.py
cloudscraper/intelligent_challenge_system.py
cloudscraper/js_challenge_solver.py
cloudscraper/jsd_solver.py
cloudscraper/lz_string_custom.py
cloudscraper/metrics.py
cloudscraper/ml_optimization.py
cloudscraper/performance.py
cloudscraper/playwright_bypass.py
cloudscraper/proxy_manager.py
cloudscraper/rate_limiter.py
cloudscraper/session_pool.py
cloudscraper/setup.py
cloudscraper/stealth.py
cloudscraper/tls_fingerprinting.py
cloudscraper/tls_rotator.py
cloudscraper/trust_builder.py
cloudscraper/turnstile.py
cloudscraper/captcha/2captcha.py
cloudscraper/captcha/9kw.py
cloudscraper/captcha/__init__.py
cloudscraper/captcha/ai_hybrid.py
cloudscraper/captcha/ai_obj_det.py
cloudscraper/captcha/ai_ocr.py
cloudscraper/captcha/anticaptcha.py
cloudscraper/captcha/capmonster.py
cloudscraper/captcha/capsolver.py
cloudscraper/captcha/deathbycaptcha.py
cloudscraper/examples/advanced_usage.py
cloudscraper/examples/async_example.py
cloudscraper/examples/enhanced_bypass_demo.py
cloudscraper/examples/turnstile_example.py
cloudscraper/interpreters/__init__.py
cloudscraper/interpreters/chakracore.py
cloudscraper/interpreters/encapsulated.py
cloudscraper/interpreters/js2py.py
cloudscraper/interpreters/js2py_interpreter.py
cloudscraper/interpreters/jsunfuck.py
ai_cloudscraper-3.8.1.dist-info/METADATA
ai_cloudscraper-3.8.1.dist-info/WHEEL
ai_cloudscraper-3.8.1.dist-info/top_level.txt
ai_cloudscraper-3.8.1.dist-info/RECORD
