Metadata-Version: 2.4
Name: ai-cloudscraper
Version: 3.8.1
Summary: Enhanced Python library to bypass Cloudflare's anti-bot protection with cutting-edge anti-detection technologies, including TLS fingerprinting, ML optimization, behavioral simulation, and 10 industrial-strength bypass strategies.
Home-page: https://github.com/zinzied/cloudscraper
Author: Zied Boughdir
Author-email: Zied Boughdir <zinzied@gmail.com>
Maintainer-email: Zied Boughdir <zinzied@gmail.com>
License: MIT
Project-URL: Homepage, https://github.com/zinzied/cloudscraper
Project-URL: Repository, https://github.com/zinzied/cloudscraper.git
Project-URL: Issues, https://github.com/zinzied/cloudscraper/issues
Project-URL: Changelog, https://github.com/zinzied/cloudscraper/blob/master/CHANGELOG.md
Keywords: cloudflare,scraping,ddos,scrape,webscraper,anti-bot,waf,iuam,bypass,challenge,tls-fingerprinting,anti-detection,stealth,machine-learning,behavioral-simulation,canvas-spoofing,webgl-spoofing,fingerprint-resistance,automation,turnstile,cookie-persistence,hybrid-solver,browser-automation,circuit-breaker,session-pool,rate-limiter,challenge-prediction
Classifier: Development Status :: 5 - Production/Stable
Classifier: Intended Audience :: Developers
Classifier: Natural Language :: English
Classifier: License :: OSI Approved :: MIT License
Classifier: Operating System :: OS Independent
Classifier: Programming Language :: Python
Classifier: Programming Language :: Python :: 3
Classifier: Programming Language :: Python :: 3.8
Classifier: Programming Language :: Python :: 3.9
Classifier: Programming Language :: Python :: 3.10
Classifier: Programming Language :: Python :: 3.11
Classifier: Programming Language :: Python :: 3.12
Classifier: Programming Language :: Python :: 3.13
Classifier: Topic :: Internet :: WWW/HTTP
Classifier: Topic :: Software Development :: Libraries :: Application Frameworks
Classifier: Topic :: Software Development :: Libraries :: Python Modules
Classifier: Topic :: Security
Classifier: Topic :: System :: Networking
Classifier: Environment :: Web Environment
Classifier: Framework :: AsyncIO
Requires-Python: >=3.8
License-File: LICENSE
Requires-Dist: requests>=2.32.0
Requires-Dist: requests-toolbelt>=1.0.0
Requires-Dist: pyparsing>=3.2.0
Requires-Dist: pyOpenSSL>=24.2.0
Requires-Dist: pycryptodome>=3.23.0
Requires-Dist: js2py>=0.74
Requires-Dist: brotli>=1.1.0
Requires-Dist: certifi>=2024.12.14
Requires-Dist: aiohttp>=3.11.0
Requires-Dist: asyncio-throttle>=1.0.2
Requires-Dist: typing-extensions>=4.12.0
Requires-Dist: ai-urllib4>=2.1.5
Provides-Extra: dev
Requires-Dist: pytest>=8.3.0; extra == "dev"
Requires-Dist: pytest-cov>=6.0.0; extra == "dev"
Requires-Dist: pytest-xdist>=3.6.0; extra == "dev"
Requires-Dist: pytest-asyncio>=0.24.0; extra == "dev"
Requires-Dist: black>=25.1.0; extra == "dev"
Requires-Dist: isort>=5.13.0; extra == "dev"
Requires-Dist: flake8>=7.1.0; extra == "dev"
Requires-Dist: mypy>=1.13.0; extra == "dev"
Requires-Dist: pre-commit>=4.0.0; extra == "dev"
Requires-Dist: bandit[toml]>=1.8.0; extra == "dev"
Requires-Dist: safety>=3.2.0; extra == "dev"
Requires-Dist: ruff>=0.8.0; extra == "dev"
Provides-Extra: test
Requires-Dist: pytest>=8.3.0; extra == "test"
Requires-Dist: pytest-cov>=6.0.0; extra == "test"
Requires-Dist: pytest-xdist>=3.6.0; extra == "test"
Requires-Dist: pytest-asyncio>=0.24.0; extra == "test"
Requires-Dist: responses>=0.25.0; extra == "test"
Requires-Dist: aioresponses>=0.7.8; extra == "test"
Requires-Dist: pytest-mock>=3.14.0; extra == "test"
Requires-Dist: httpx>=0.28.0; extra == "test"
Provides-Extra: ai
Requires-Dist: ddddocr; extra == "ai"
Requires-Dist: ultralytics; extra == "ai"
Requires-Dist: pillow>=10.0.0; extra == "ai"
Provides-Extra: browser
Requires-Dist: playwright>=1.40.0; extra == "browser"
Dynamic: author
Dynamic: home-page
Dynamic: license-file
Dynamic: requires-python
